miniflux.py
miniflux-1.1.5.dist-info/licenses/LICENSE.txt
miniflux-1.1.5.dist-info/METADATA
miniflux-1.1.5.dist-info/WHEEL
miniflux-1.1.5.dist-info/top_level.txt
miniflux-1.1.5.dist-info/RECORD
