Metadata-Version: 2.4
Name: miniflux
Version: 1.1.5
Summary: Client library for Miniflux
Author-email: Frédéric Guillot <fred@miniflux.net>
License: The MIT License (MIT)
Project-URL: Homepage, https://github.com/miniflux/python-client
Project-URL: Bug Reports, https://github.com/miniflux/python-client/issues
Project-URL: Source, https://github.com/miniflux/python-client
Keywords: rss,atom,rdf,jsonfeed,feed,miniflux
Classifier: Intended Audience :: Developers
Classifier: Programming Language :: Python :: 3 :: Only
Requires-Python: >=3.8
License-File: LICENSE.txt
Requires-Dist: requests
Dynamic: license-file
